{
  "metadata": {
    "version": "2.0.0",
    "updated": "2025-12-08",
    "description": "Climate zone classifications for TILE mapping system",
    "total_zones": 18,
    "coordinate_system": "TILE-based (no lat/long)",
    "usage": "Climate zones mapped to TILE grid for world generation"
  },
  "climate_zones": [
    {
      "id": "tropical_rainforest",
      "name": "Tropical Rainforest",
      "koppen_code": "Af",
      "temp_range_c": {
        "min": 18,
        "max": 35
      },
      "annual_rainfall_mm": {
        "min": 2000,
        "max": 10000
      },
      "description": "Hot and humid year-round with heavy rainfall",
      "vegetation": "Dense rainforest",
      "example_tiles": [
        "AA100-100",
        "AB105-100",
        "AC110-100"
      ],
      "season_count": 1,
      "color_code": "dark_green"
    },
    {
      "id": "tropical_monsoon",
      "name": "Tropical Monsoon",
      "koppen_code": "Am",
      "temp_range_c": {
        "min": 18,
        "max": 38
      },
      "annual_rainfall_mm": {
        "min": 1500,
        "max": 4000
      },
      "description": "Hot with distinct wet and dry seasons",
      "vegetation": "Seasonal forests",
      "season_count": 2,
      "color_code": "green",
      "example_tiles": []
    },
    {
      "id": "tropical_savanna",
      "name": "Tropical Savanna",
      "koppen_code": "Aw",
      "temp_range_c": {
        "min": 15,
        "max": 35
      },
      "annual_rainfall_mm": {
        "min": 500,
        "max": 1500
      },
      "description": "Warm with pronounced dry season",
      "vegetation": "Grasslands with scattered trees",
      "season_count": 2,
      "color_code": "yellow_green",
      "example_tiles": []
    },
    {
      "id": "hot_desert",
      "name": "Hot Desert",
      "koppen_code": "BWh",
      "temp_range_c": {
        "min": 5,
        "max": 50
      },
      "annual_rainfall_mm": {
        "min": 0,
        "max": 250
      },
      "description": "Extremely hot and dry",
      "vegetation": "Sparse desert plants",
      "season_count": 2,
      "color_code": "yellow",
      "example_tiles": []
    },
    {
      "id": "cold_desert",
      "name": "Cold Desert",
      "koppen_code": "BWk",
      "temp_range_c": {
        "min": -20,
        "max": 30
      },
      "annual_rainfall_mm": {
        "min": 0,
        "max": 250
      },
      "description": "Cold winters, hot summers, very dry",
      "vegetation": "Minimal desert scrub",
      "season_count": 4,
      "color_code": "tan",
      "example_tiles": []
    },
    {
      "id": "semi_arid",
      "name": "Semi-Arid Steppe",
      "koppen_code": "BS",
      "temp_range_c": {
        "min": -10,
        "max": 40
      },
      "annual_rainfall_mm": {
        "min": 250,
        "max": 500
      },
      "description": "Low rainfall, grassland transition zone",
      "vegetation": "Short grasses and shrubs",
      "season_count": 4,
      "color_code": "brown",
      "example_tiles": []
    },
    {
      "id": "mediterranean",
      "name": "Mediterranean",
      "koppen_code": "Cs",
      "temp_range_c": {
        "min": 5,
        "max": 30
      },
      "annual_rainfall_mm": {
        "min": 400,
        "max": 900
      },
      "description": "Hot dry summers, mild wet winters",
      "vegetation": "Chaparral, olive groves",
      "season_count": 4,
      "color_code": "olive",
      "example_tiles": []
    },
    {
      "id": "humid_subtropical",
      "name": "Humid Subtropical",
      "koppen_code": "Cfa",
      "temp_range_c": {
        "min": -5,
        "max": 35
      },
      "annual_rainfall_mm": {
        "min": 800,
        "max": 2000
      },
      "description": "Hot humid summers, mild winters",
      "vegetation": "Mixed forests",
      "season_count": 4,
      "color_code": "green",
      "example_tiles": []
    },
    {
      "id": "oceanic",
      "name": "Oceanic",
      "koppen_code": "Cfb",
      "temp_range_c": {
        "min": 0,
        "max": 25
      },
      "annual_rainfall_mm": {
        "min": 800,
        "max": 2500
      },
      "description": "Mild temperatures year-round, frequent rain",
      "vegetation": "Temperate rainforest",
      "season_count": 4,
      "color_code": "dark_green",
      "example_tiles": []
    },
    {
      "id": "continental_warm",
      "name": "Warm Continental",
      "koppen_code": "Dfa",
      "temp_range_c": {
        "min": -25,
        "max": 35
      },
      "annual_rainfall_mm": {
        "min": 500,
        "max": 1000
      },
      "description": "Hot summers, cold snowy winters",
      "vegetation": "Deciduous and mixed forests",
      "season_count": 4,
      "color_code": "light_green",
      "example_tiles": []
    },
    {
      "id": "continental_cool",
      "name": "Cool Continental",
      "koppen_code": "Dfb",
      "temp_range_c": {
        "min": -35,
        "max": 25
      },
      "annual_rainfall_mm": {
        "min": 400,
        "max": 800
      },
      "description": "Cool summers, very cold winters",
      "vegetation": "Boreal forest (taiga)",
      "season_count": 4,
      "color_code": "forest_green",
      "example_tiles": []
    },
    {
      "id": "subarctic",
      "name": "Subarctic",
      "koppen_code": "Dfc",
      "temp_range_c": {
        "min": -50,
        "max": 20
      },
      "annual_rainfall_mm": {
        "min": 200,
        "max": 600
      },
      "description": "Short cool summers, long severe winters",
      "vegetation": "Sparse boreal forest",
      "season_count": 2,
      "color_code": "gray_green",
      "example_tiles": []
    },
    {
      "id": "tundra",
      "name": "Tundra",
      "koppen_code": "ET",
      "temp_range_c": {
        "min": -50,
        "max": 10
      },
      "annual_rainfall_mm": {
        "min": 100,
        "max": 400
      },
      "description": "No true summer, permafrost",
      "vegetation": "Mosses, lichens, low shrubs",
      "season_count": 2,
      "color_code": "white_gray",
      "example_tiles": []
    },
    {
      "id": "ice_cap",
      "name": "Ice Cap",
      "koppen_code": "EF",
      "temp_range_c": {
        "min": -70,
        "max": 0
      },
      "annual_rainfall_mm": {
        "min": 50,
        "max": 500
      },
      "description": "Permanent ice and snow",
      "vegetation": "None",
      "season_count": 2,
      "color_code": "white",
      "example_tiles": []
    },
    {
      "id": "highland",
      "name": "Highland",
      "koppen_code": "H",
      "temp_range_c": {
        "min": -30,
        "max": 25
      },
      "annual_rainfall_mm": {
        "min": 200,
        "max": 3000
      },
      "description": "Varies with altitude and location",
      "vegetation": "Varies from forest to alpine",
      "season_count": 4,
      "color_code": "brown_white",
      "example_tiles": []
    },
    {
      "id": "humid_continental_dry",
      "name": "Humid Continental (Dry)",
      "koppen_code": "Dwa",
      "temp_range_c": {
        "min": -30,
        "max": 30
      },
      "annual_rainfall_mm": {
        "min": 300,
        "max": 700
      },
      "description": "Dry winters, warm summers",
      "vegetation": "Mixed grassland and forest",
      "season_count": 4,
      "color_code": "tan_green",
      "example_tiles": []
    },
    {
      "id": "monsoon_influenced",
      "name": "Monsoon-Influenced",
      "koppen_code": "Cwa",
      "temp_range_c": {
        "min": 0,
        "max": 35
      },
      "annual_rainfall_mm": {
        "min": 600,
        "max": 1500
      },
      "description": "Dry winters, wet summers",
      "vegetation": "Seasonal forests",
      "season_count": 2,
      "color_code": "green",
      "example_tiles": []
    },
    {
      "id": "alpine",
      "name": "Alpine",
      "koppen_code": "H",
      "temp_range_c": {
        "min": -20,
        "max": 15
      },
      "annual_rainfall_mm": {
        "min": 500,
        "max": 2000
      },
      "description": "High altitude, cold year-round",
      "vegetation": "Alpine meadows, bare rock",
      "season_count": 2,
      "color_code": "gray_white",
      "example_tiles": []
    }
  ],
  "koppen_classification": {
    "A": {
      "group": "Tropical",
      "description": "Average temp > 18\u00b0C year-round"
    },
    "B": {
      "group": "Arid",
      "description": "Evaporation exceeds precipitation"
    },
    "C": {
      "group": "Temperate",
      "description": "Coldest month 0-18\u00b0C"
    },
    "D": {
      "group": "Continental",
      "description": "Coldest month < 0\u00b0C, warmest > 10\u00b0C"
    },
    "E": {
      "group": "Polar",
      "description": "Warmest month < 10\u00b0C"
    }
  },
  "precipitation_patterns": {
    "year_round": {
      "description": "Rainfall distributed throughout year",
      "climates": [
        "tropical_rainforest",
        "oceanic"
      ]
    },
    "summer_wet": {
      "description": "Most rain in summer months",
      "climates": [
        "tropical_monsoon",
        "humid_subtropical",
        "monsoon_influenced"
      ]
    },
    "winter_wet": {
      "description": "Most rain in winter months",
      "climates": [
        "mediterranean"
      ]
    },
    "minimal": {
      "description": "Very little precipitation",
      "climates": [
        "hot_desert",
        "cold_desert",
        "ice_cap"
      ]
    }
  },
  "temperature_categories": {
    "extreme_cold": {
      "range": "< -30\u00b0C",
      "description": "Arctic/Antarctic conditions"
    },
    "very_cold": {
      "range": "-30\u00b0C to -10\u00b0C",
      "description": "Subarctic winter"
    },
    "cold": {
      "range": "-10\u00b0C to 0\u00b0C",
      "description": "Cold winter"
    },
    "cool": {
      "range": "0\u00b0C to 10\u00b0C",
      "description": "Temperate cool"
    },
    "mild": {
      "range": "10\u00b0C to 20\u00b0C",
      "description": "Comfortable"
    },
    "warm": {
      "range": "20\u00b0C to 30\u00b0C",
      "description": "Warm tropical"
    },
    "hot": {
      "range": "30\u00b0C to 40\u00b0C",
      "description": "Hot desert/tropical"
    },
    "extreme_heat": {
      "range": "> 40\u00b0C",
      "description": "Extreme desert heat"
    }
  }
}