{
  "color_palettes": {
    "metadata": {
      "version": "2.0",
      "created": "2025-08-21",
      "description": "uDOS Final Color Management System - Single professional palette",
      "last_updated": "2025-08-21T23:15:00Z"
    },
    "udos_final": {
      "name": "uDOS Final Palette",
      "description": "Final professional color palette for uDOS system",
      "type": "professional",
      "colors": {
        "BLACK": {"hex": "#000000", "rgb": [0, 0, 0], "name": "Pure Black"},
        "WHITE": {"hex": "#FFFFFF", "rgb": [255, 255, 255], "name": "Pure White"},
        "CINNAMON_SATIN": {"hex": "#D45979", "rgb": [212, 89, 121], "cmyk": [0, 58, 43, 17], "hsv": [344, 58, 83], "ral": "4003", "pantone": "702 C"},
        "INDIAN_YELLOW": {"hex": "#E8A05D", "rgb": [232, 160, 93], "cmyk": [0, 31, 60, 9], "hsv": [29, 60, 91], "ral": "1034", "pantone": "7411 C"},
        "CARAMEL": {"hex": "#F8DC93", "rgb": [248, 220, 147], "cmyk": [0, 11, 41, 3], "hsv": [43, 41, 97], "ral": "1014", "pantone": "1205 C"},
        "SHINY_SHAMROCK": {"hex": "#4DA378", "rgb": [77, 163, 120], "cmyk": [53, 0, 26, 36], "hsv": [150, 53, 64], "ral": "6033", "pantone": "7723 C"},
        "LIBERTY": {"hex": "#4B5798", "rgb": [75, 87, 152], "cmyk": [51, 43, 0, 40], "hsv": [231, 51, 60], "ral": "5023", "pantone": "7670 C"},
        "PURPLE_PLUM": {"hex": "#A25FAD", "rgb": [162, 95, 173], "cmyk": [6, 45, 0, 32], "hsv": [292, 45, 68], "ral": "4005", "pantone": "2583 C"}
      },
      "usage": {
        "primary": "SHINY_SHAMROCK",
        "secondary": "LIBERTY", 
        "accent": "CINNAMON_SATIN",
        "warning": "INDIAN_YELLOW",
        "highlight": "CARAMEL",
        "special": "PURPLE_PLUM",
        "background": "BLACK",
        "text": "WHITE"
      },
      "themes": {
        "default": {
          "bg_primary": "BLACK",
          "bg_secondary": "LIBERTY",
          "text_primary": "WHITE",
          "text_secondary": "CARAMEL",
          "accent": "SHINY_SHAMROCK",
          "highlight": "CINNAMON_SATIN",
          "warning": "INDIAN_YELLOW",
          "special": "PURPLE_PLUM"
        }
      }
    },
    "css_variables": {
      "udos_final": {
        "color-black": "#000000",
        "color-white": "#FFFFFF", 
        "color-cinnamon": "#D45979",
        "color-yellow": "#E8A05D",
        "color-caramel": "#F8DC93",
        "color-green": "#4DA378",
        "color-blue": "#4B5798",
        "color-purple": "#A25FAD",
        "color-grey": "#666666",
        "color-light-grey": "#999999",
        "color-dark-grey": "#333333"
      }
    }
  }
}
